bolsa/__init__.py
bolsa/consultas.py
bolsa/negociacion.py
bolsa_stgo-0.1.0.dist-info/LICENSE
bolsa_stgo-0.1.0.dist-info/METADATA
bolsa_stgo-0.1.0.dist-info/WHEEL
bolsa_stgo-0.1.0.dist-info/top_level.txt
bolsa_stgo-0.1.0.dist-info/RECORD
