Metadata-Version: 2.1
Name: bolsa-stgo
Version: 0.1.0
Summary: SDK de la API de la bolsa de Santiago.
Home-page: https://github.com/LautaroParada/bolsa-santiago
Author: Lautaro Parada Opazo
Author-email: lautaro.parada.opazo@gmail.com
License: MIT License
Platform: UNKNOWN
